gymDSM/__init__.py
gymDSM/gymDSM.py
gymdsm-1.0.0.dist-info/licenses/LICENSE
gymdsm-1.0.0.dist-info/METADATA
gymdsm-1.0.0.dist-info/WHEEL
gymdsm-1.0.0.dist-info/top_level.txt
gymdsm-1.0.0.dist-info/RECORD
