Metadata-Version: 2.4
Name: gymDSM
Version: 1.0.0
Summary: gymDSM (Didactically Supercharged Mod): a small library that provides didactically enhanced OpenAI Gym environments (e.g., a MountainCar variant whose render color shows the last action).
Home-page: https://github.com/DanielSaromo/gymDSM
Author: Daniel Saromo
Author-email: danielsaromo@gmail.com
Classifier: Programming Language :: Python :: 3
Classifier: License :: OSI Approved :: MIT License
Classifier: Operating System :: OS Independent
Classifier: Topic :: Scientific/Engineering :: Artificial Intelligence
Requires-Python: >=3.7
License-File: LICENSE
Requires-Dist: gym==0.22
Requires-Dist: numpy
Provides-Extra: render
Requires-Dist: pygame; extra == "render"
Dynamic: author
Dynamic: author-email
Dynamic: classifier
Dynamic: description
Dynamic: description-content-type
Dynamic: home-page
Dynamic: license-file
Dynamic: provides-extra
Dynamic: requires-dist
Dynamic: requires-python
Dynamic: summary
